.bumpversion.cfg
.cookiecutterrc
.coveragerc
.editorconfig
.travis.yml
AUTHORS.rst
CHANGELOG.rst
CONTRIBUTING.rst
LICENSE
MANIFEST.in
README.rst
appveyor.yml
setup.cfg
setup.py
tox.ini
ci/appveyor-bootstrap.py
ci/appveyor-download.py
ci/appveyor-with-compiler.cmd
ci/bootstrap.py
ci/templates/.travis.yml
ci/templates/appveyor.yml
docs/authors.rst
docs/changelog.rst
docs/conf.py
docs/contributing.rst
docs/index.rst
docs/installation.rst
docs/internals.rst
docs/license.rst
docs/namespace.rst
docs/readme.rst
docs/requirements.txt
docs/spelling_wordlist.txt
docs/usage.rst
docs/reference/index.rst
docs/reference/sunvosc.rst
examples/singlenote.py
src/sunvosc/__init__.py
src/sunvosc/__main__.py
src/sunvosc/cli.py
src/sunvosc/dispatcher.py
src/sunvosc.egg-info/PKG-INFO
src/sunvosc.egg-info/SOURCES.txt
src/sunvosc.egg-info/dependency_links.txt
src/sunvosc.egg-info/entry_points.txt
src/sunvosc.egg-info/not-zip-safe
src/sunvosc.egg-info/requires.txt
src/sunvosc.egg-info/top_level.txt
tests/__init__.py
tests/test_nothing.py