Metadata-Version: 1.1
Name: sunvosc
Version: 0.1.0
Summary: Bidirectional OSC bridge for SunVox DLL
Home-page: https://github.com/metrasynth/sunvosc
Author: Matthew Scott
Author-email: matt@11craft.com
License: MIT
Keywords: sunvox,osc,audio,music,sound,tracker
Platform: UNKNOWN
Classifier: Development Status :: 5 - Production/Stable
Classifier: Intended Audience :: Developers
Classifier: License :: OSI Approved :: MIT License
Classifier: Operating System :: Unix
Classifier: Operating System :: POSIX
Classifier: Operating System :: Microsoft :: Windows
Classifier: Programming Language :: Python
Classifier: Programming Language :: Python :: 3.5
Classifier: Programming Language :: Python :: Implementation :: CPython
Classifier: Topic :: Utilities
